timework/__init__.py
timework/test_decorator.py
timework/test_with-statement.py
timework/timework.py
timework-0.4.3.dist-info/LICENSE
timework-0.4.3.dist-info/METADATA
timework-0.4.3.dist-info/WHEEL
timework-0.4.3.dist-info/top_level.txt
timework-0.4.3.dist-info/RECORD
