Metadata-Version: 2.1
Name: timework
Version: 0.4.3
Summary: measure / limit execution time using with-statements or decorators, cross-platform
Home-page: https://github.com/bugstop/python-timework
Author: bugstop
Author-email: pypi@isaacx.com
License: UNKNOWN
Platform: UNKNOWN
Classifier: Programming Language :: Python :: 3
Classifier: License :: OSI Approved :: MIT License
Classifier: Operating System :: OS Independent
Requires-Python: >=3.5
